{"basics":{"name":"Jeremias Berg","image":"","email":"jeremiasberg@gmail.com","phone":"(+358) 50-5767581","url":"https://www.jeremiasberg.com","summary":"A post doctoral researcher and university lecturer at the University of Helsinki","location":{"address":"Pietari Kalmin katu 5","postalCode":"","city":"Helsinki","countryCode":"FIN","region":"Helsinki"},"profiles":[]},"work":[{"name":"University of Helsinki","position":"Postdoctoral Researcher","url":"https://www.helsinki.fi/fi/matemaattis-luonnontieteellinen-tiedekunta/tiedekunta/tietojenkasittelytiede","startDate":"2021-09-01","endDate":"2024-08-31","summary":"Funded under a postdoctoral grant from the Research Council of Finland.","highlights":["best paper at SAT 2023","2020 ACP doctoral research award"]},{"name":"University of Helsinki","position":"University Lecturer","url":"https://www.helsinki.fi/fi/matemaattis-luonnontieteellinen-tiedekunta/tiedekunta/tietojenkasittelytiede","startDate":"2022-09-01","endDate":"2027-08-31","summary":"30% part-time position","highlights":[]}],"volunteer":[{"organization":"Young Academy of Finland","position":"Board Member","url":"https://nuortentiedeakatemia.fi/en/","startDate":"2023-09-01","endDate":"2024-08-31","summary":"In charge of science education","highlights":[]}],"education":[{"institution":"University of Helsinki","location":"Helsinki, Finland","url":"https://www.helsinki.fi/fi/matemaattis-luonnontieteellinen-tiedekunta/tiedekunta/tietojenkasittelytiede","area":"Computer Science","studyType":"PhD","startDate":"2015-01-01","endDate":"2018-06-12","score":"10","courses":[]}],"awards":[{"title":"Doctoral Research Award","date":"2020","awarder":"Association of Constraint Programming (ACP)","url":"https://www.a4cp.org/awards/doctoral-research-award","summary":"The ACP is the foremost international organization in the research field of constraint programming. The doctoral research award is given to one PhD thesis annually"}],"certificates":[],"skills":[{"name":"Computer Science","level":"PhD","icon":"fa-solid fa-hashtag","keywords":["Combinatorial Optimization","Constraint Optimization","Automated Reasoning","Maximum Satisfiability","Pseudo Boolean Optimization"]}],"languages":[{"language":"Finnish","fluency":"Native speaker","icon":""},{"language":"Swedish","fluency":"Native speaker","icon":""},{"language":"English","fluency":"Fluent","icon":""}],"interests":[{"name":"Climbing","icon":"fa-solid fa-tag","keywords":["Lead Climbing","Outdoor Climbing"]},{"name":"Frisbeegolf","icon":"fa-solid fa-tag","keywords":[]}],"references":[{"name":"Professor Peter Stuckey","icon":"fa-solid fa-laptop","reference":"Peter.Stuckeymonashedu"},{"name":"Professor Jakob Nordström","icon":"fa-solid fa-laptop","reference":"jn at-sign di dot ku dot dk or"},{"name":"Professor Matti Järvisalo","icon":"fa-solid fa-laptop","reference":"matti.jarvisalo[AT]helsinki.fi"}],"projects":[{"name":"Next-Generation Combinatorial Optimization","summary":"Quantum computing is the use of quantum-mechanical phenomena such as superposition and entanglement to perform computation. Computers that perform quantum computations are known as quantum computers.","highlights":["Quantum Teleportation","Quantum Cryptography"],"startDate":"2018-01-01","endDate":"2018-01-01","url":"https://example.com"}]}